{
  "ledgerID": "0x01",
  "nettyMode": "DEV",
  "chainId": 298,
  "logPeriod": 1,
  "exportPeriodSecs": 400,
  "maxSizeKb": 2048,
  "streamExtension": "rcd.gz",
  "sidecarEnabled": true,
  "nodeImageTag": "0.41.0-alpha.5",
  "havegedImageTag": "0.41.0-alpha.5",
  "uploaderImageTag": "0.7.0",
  "mirrorImageTag": "0.87.0-rc3",
  "relayImageTag": "0.30.0-rc1",
  "pythonVersion": "python3.7",
  "mirrorNodeExplorerImageTag": "23.5.0",
  "transactionMaxBytes": "6144",
  "features": {
    "compressFilesOnCreation": true,
    "compressOnCreation": true,
    "maxNumWithHapiSigsAccess": "0"
  }
}
